Workbook

Sheet START HERE
A1: STONE COLUMN - COST-PLUS ESTIMATE & PROGRESS BILLING
A4: The budget creates the estimate. Actual QuickBooks job costs create the invoice.
A6: STEP | B6: WORKFLOW
A7: 1 | B7: Complete Project Setup. Yellow cells are user inputs.
A8: 2 | B8: Build the internal BUDGET by entering original budget, adjustments, discounts, descriptions, and billing flags.
A9: 3 | B9: The ESTIMATE automatically summarizes that budget and adds the estimated management fee. It clearly states that figures are estimates only.
A10: 4 | B10: Export the latest QuickBooks Job Estimates vs. Actuals report. Copy the entire Sheet1 report and paste it into QB JOB COST IMPORT beginning at cell A6.
A11: 5 | B11: COST RECONCILIATION matches QuickBooks actual costs to the four-digit cost codes and subtracts costs already recorded in DRAW HISTORY.
A12: 6 | B12: Review INVOICE and INVOICE DETAIL. The amount due is actual new cost plus the management fee, less any credit applied this draw.
A13: 7 | B13: After sending the invoice, copy the Current Draw Cost column from COST RECONCILIATION and paste VALUES ONLY into the matching draw column in DRAW HISTORY.
A14: 8 | B14: For the next draw, replace the QB import with the newest cumulative report, select the next draw number, and repeat.
A16: CONTROL: Do not overwrite prior draw-history columns. That history is what prevents the same cumulative QuickBooks costs from being billed twice. Budget overruns are highlighted but remain billable under the cost-plus model.

Sheet Project Setup
A1: PROJECT SETUP
A4: Company Name | B4: STONE COLUMN CUSTOM HOMES + REMODELING
A5: Payable To | B5: Stone Column Properties, LLC.
A6: Company Address | B6: 7772 Turner Rd.
A7: Company City / State / ZIP | B7: Woodstock, GA 30188
A8: Phone | B8: (404) 867-7890
A9: Email
A10: Customer Name
A11: Customer Address
A12: Customer City / State / ZIP
A13: Customer Email
A14: Project Name
A15: Project Address
A16: Estimate #
A17: Estimate Date
A18: Management Fee % | B18: 0.18
A19: Estimated Deposit % | B19: 0.4
A20: Estimate Terms | B20: Cost-plus arrangement. Budget amounts are estimates only. Owner is billed for actual project costs incurred plus the stated project-management fee.
A21: CURRENT DRAW NUMBER | B21: 1
A22: Invoice # Prefix
A23: Invoice Date
A24: Due Date
A25: Credit / Deposit Applied This Draw | B25: 0
A26: Payment Terms | B26: Due upon receipt

Sheet BUDGET
A1: INTERNAL COST-PLUS PROJECT BUDGET
A3: Yellow = input | Blue = calculated | Budget is an estimate and does not cap reimbursable actual cost
A5: Code | B5: Activity | C5: Original Budget | D5: Description / Scope | E5: Adjustment | F5: Reason | G5: Vendor Discount | H5: Adjusted Budget | I5: Include in Estimate? | J5: Billable Cost? | K5: Division | L5: Current QB Actual | M5: Prior Billed | N5: Current Draw Cost | O5: Budget Variance | P5: Status
A6: 1010 | B6: Plan / Site Plans | C6: 0 | E6: 0 | G6: 0 | H6: =C6+E6-G6 -> 0 | I6: Yes | J6: Yes | K6: Preconstruction & General | L6: ='COST RECONCILIATION'!D6 -> 0 | M6: ='COST RECONCILIATION'!E6 -> 0 | N6: ='COST RECONCILIATION'!F6 -> 0 | O6: =L6-H6 -> 0 | P6: =IF(J6="No","EXCLUDED",IF(L6>H6,"OVER BUDGET","OK")) -> OK
A7: 1011 | B7: Permits/Fees/Water/Sewer | C7: 0 | E7: 0 | G7: 0 | H7: =C7+E7-G7 -> 0 | I7: Yes | J7: Yes | K7: Preconstruction & General | L7: ='COST RECONCILIATION'!D7 -> 0 | M7: ='COST RECONCILIATION'!E7 -> 0 | N7: ='COST RECONCILIATION'!F7 -> 0 | O7: =L7-H7 -> 0 | P7: =IF(J7="No","EXCLUDED",IF(L7>H7,"OVER BUDGET","OK")) -> OK
A8: 1020 | B8: Surveys | C8: 0 | E8: 0 | G8: 0 | H8: =C8+E8-G8 -> 0 | I8: Yes | J8: Yes | K8: Preconstruction & General | L8: ='COST RECONCILIATION'!D8 -> 0 | M8: ='COST RECONCILIATION'!E8 -> 0 | N8: ='COST RECONCILIATION'!F8 -> 0 | O8: =L8-H8 -> 0 | P8: =IF(J8="No","EXCLUDED",IF(L8>H8,"OVER BUDGET","OK")) -> OK
A9: 1070 | B9: Builders Risk Insurance | C9: 0 | E9: 0 | G9: 0 | H9: =C9+E9-G9 -> 0 | I9: Yes | J9: Yes | K9: Preconstruction & General | L9: ='COST RECONCILIATION'!D9 -> 0 | M9: ='COST RECONCILIATION'!E9 -> 0 | N9: ='COST RECONCILIATION'!F9 -> 0 | O9: =L9-H9 -> 0 | P9: =IF(J9="No","EXCLUDED",IF(L9>H9,"OVER BUDGET","OK")) -> OK
A10: 1080 | B10: Reinspection Fees | C10: 0 | E10: 0 | G10: 0 | H10: =C10+E10-G10 -> 0 | I10: Yes | J10: Yes | K10: Preconstruction & General | L10: ='COST RECONCILIATION'!D10 -> 0 | M10: ='COST RECONCILIATION'!E10 -> 0 | N10: ='COST RECONCILIATION'!F10 -> 0 | O10: =L10-H10 -> 0 | P10: =IF(J10="No","EXCLUDED",IF(L10>H10,"OVER BUDGET","OK")) -> OK
A11: 2010 | B11: Grading - Clear Lot | C11: 0 | E11: 0 | G11: 0 | H11: =C11+E11-G11 -> 0 | I11: Yes | J11: Yes | K11: Sitework | L11: ='COST RECONCILIATION'!D11 -> 0 | M11: ='COST RECONCILIATION'!E11 -> 0 | N11: ='COST RECONCILIATION'!F11 -> 0 | O11: =L11-H11 -> 0 | P11: =IF(J11="No","EXCLUDED",IF(L11>H11,"OVER BUDGET","OK")) -> OK
A12: 2011 | B12: Grading - Haul Debris | C12: 0 | E12: 0 | G12: 0 | H12: =C12+E12-G12 -> 0 | I12: Yes | J12: Yes | K12: Sitework | L12: ='COST RECONCILIATION'!D12 -> 0 | M12: ='COST RECONCILIATION'!E12 -> 0 | N12: ='COST RECONCILIATION'!F12 -> 0 | O12: =L12-H12 -> 0 | P12: =IF(J12="No","EXCLUDED",IF(L12>H12,"OVER BUDGET","OK")) -> OK
A13: 2012 | B13: Grading - Cut Foundation | C13: 0 | E13: 0 | G13: 0 | H13: =C13+E13-G13 -> 0 | I13: Yes | J13: Yes | K13: Sitework | L13: ='COST RECONCILIATION'!D13 -> 0 | M13: ='COST RECONCILIATION'!E13 -> 0 | N13: ='COST RECONCILIATION'!F13 -> 0 | O13: =L13-H13 -> 0 | P13: =IF(J13="No","EXCLUDED",IF(L13>H13,"OVER BUDGET","OK")) -> OK
A14: 2013 | B14: Grading - Backfill Found | C14: 0 | E14: 0 | G14: 0 | H14: =C14+E14-G14 -> 0 | I14: Yes | J14: Yes | K14: Sitework | L14: ='COST RECONCILIATION'!D14 -> 0 | M14: ='COST RECONCILIATION'!E14 -> 0 | N14: ='COST RECONCILIATION'!F14 -> 0 | O14: =L14-H14 -> 0 | P14: =IF(J14="No","EXCLUDED",IF(L14>H14,"OVER BUDGET","OK")) -> OK
A15: 2014 | B15: Grading - Cut Drive | C15: 0 | E15: 0 | G15: 0 | H15: =C15+E15-G15 -> 0 | I15: Yes | J15: Yes | K15: Sitework | L15: ='COST RECONCILIATION'!D15 -> 0 | M15: ='COST RECONCILIATION'!E15 -> 0 | N15: ='COST RECONCILIATION'!F15 -> 0 | O15: =L15-H15 -> 0 | P15: =IF(J15="No","EXCLUDED",IF(L15>H15,"OVER BUDGET","OK")) -> OK
A16: 2015 | B16: Grading - Final | C16: 0 | E16: 0 | G16: 0 | H16: =C16+E16-G16 -> 0 | I16: Yes | J16: Yes | K16: Sitework | L16: ='COST RECONCILIATION'!D16 -> 0 | M16: ='COST RECONCILIATION'!E16 -> 0 | N16: ='COST RECONCILIATION'!F16 -> 0 | O16: =L16-H16 -> 0 | P16: =IF(J16="No","EXCLUDED",IF(L16>H16,"OVER BUDGET","OK")) -> OK
A17: 2016 | B17: Grading - Misc | C17: 0 | E17: 0 | G17: 0 | H17: =C17+E17-G17 -> 0 | I17: Yes | J17: Yes | K17: Sitework | L17: ='COST RECONCILIATION'!D17 -> 0 | M17: ='COST RECONCILIATION'!E17 -> 0 | N17: ='COST RECONCILIATION'!F17 -> 0 | O17: =L17-H17 -> 0 | P17: =IF(J17="No","EXCLUDED",IF(L17>H17,"OVER BUDGET","OK")) -> OK
... A118: 9999 | B118: Transfer WIP to CGS | C118: 0 | E118: 0 | G118: 0 | H118: =C118+E118-G118 -> 0 | I118: Yes | J118: No | K118: Other Project Costs | L118: ='COST RECONCILIATION'!D118 -> 0 | M118: ='COST RECONCILIATION'!E118 -> 0 | N118: ='COST RECONCILIATION'!F118 -> 0 | O118: =L118-H118 -> 0 | P118: =IF(J118="No","EXCLUDED",IF(L118>H118,"OVER BUDGET","OK")) -> EXCLUDED
F120: ESTIMATED BILLABLE HARD COST | H120: =SUMIF(J6:J118,"Yes",H6:H118) -> 0
F121: ESTIMATED MANAGEMENT FEE | H121: =H120*'Project Setup'!B18 -> 0
F122: ESTIMATED PROJECT TOTAL | H122: =H120+H121 -> 0

Sheet QB JOB COST IMPORT
A1: QUICKBOOKS JOB COST IMPORT - CUMULATIVE ACTUALS
A3: Replace the prior import each draw. Copy the entire QuickBooks exported Sheet1 and paste beginning at A6. Keep the QuickBooks Service in column C and Actual Cost in column F. Column I parses the cost code automatically.
I5: Parsed Cost Code
I6: =IFERROR(VALUE(LEFT(TRIM(C6),4)),0) -> 0
I7: =IFERROR(VALUE(LEFT(TRIM(C7),4)),0) -> 0
I8: =IFERROR(VALUE(LEFT(TRIM(C8),4)),0) -> 0
I9: =IFERROR(VALUE(LEFT(TRIM(C9),4)),0) -> 0
I10: =IFERROR(VALUE(LEFT(TRIM(C10),4)),0) -> 0
I11: =IFERROR(VALUE(LEFT(TRIM(C11),4)),0) -> 0
I12: =IFERROR(VALUE(LEFT(TRIM(C12),4)),0) -> 0
I13: =IFERROR(VALUE(LEFT(TRIM(C13),4)),0) -> 0
I14: =IFERROR(VALUE(LEFT(TRIM(C14),4)),0) -> 0
I15: =IFERROR(VALUE(LEFT(TRIM(C15),4)),0) -> 0
I16: =IFERROR(VALUE(LEFT(TRIM(C16),4)),0) -> 0
I17: =IFERROR(VALUE(LEFT(TRIM(C17),4)),0) -> 0
... I210: =IFERROR(VALUE(LEFT(TRIM(C210),4)),0) -> 0

Sheet COST RECONCILIATION
A1: COST RECONCILIATION - BUDGET VS. QUICKBOOKS VS. PRIOR DRAWS
A4: Code | B4: Activity | C4: Adjusted Budget | D4: Current QB Actual | E4: Previously Invoiced Cost | F4: Current Draw Cost | G4: Actual vs Budget | H4: Billable? | I4: Import Match | J4: Review
A6: =BUDGET!A6 -> 1010 | B6: =BUDGET!B6 -> Plan / Site Plans | C6: =BUDGET!H6 -> 0 | D6: =SUMIF('QB JOB COST IMPORT'!$I$6:$I$210,A6,'QB JOB COST IMPORT'!$F$6:$F$210) -> 0 | E6: =SUM('DRAW HISTORY'!C6:L6) -> 0 | F6: =IF(H6="Yes",D6-E6,0) -> 0 | G6: =D6-C6 -> 0 | H6: =BUDGET!J6 -> Yes | I6: =IF(D6=0,IF(C6=0,"NO COST / NO BUDGET","NO QB ACTUAL"),"MATCHED") -> NO COST / NO BUDGET | J6: =IF(E6>D6,"PRIOR BILLING EXCEEDS QB ACTUAL",IF(G6>0,"OVER BUDGET","OK")) -> OK
A7: =BUDGET!A7 -> 1011 | B7: =BUDGET!B7 -> Permits/Fees/Water/Sewer | C7: =BUDGET!H7 -> 0 | D7: =SUMIF('QB JOB COST IMPORT'!$I$6:$I$210,A7,'QB JOB COST IMPORT'!$F$6:$F$210) -> 0 | E7: =SUM('DRAW HISTORY'!C7:L7) -> 0 | F7: =IF(H7="Yes",D7-E7,0) -> 0 | G7: =D7-C7 -> 0 | H7: =BUDGET!J7 -> Yes | I7: =IF(D7=0,IF(C7=0,"NO COST / NO BUDGET","NO QB ACTUAL"),"MATCHED") -> NO COST / NO BUDGET | J7: =IF(E7>D7,"PRIOR BILLING EXCEEDS QB ACTUAL",IF(G7>0,"OVER BUDGET","OK")) -> OK
A8: =BUDGET!A8 -> 1020 | B8: =BUDGET!B8 -> Surveys | C8: =BUDGET!H8 -> 0 | D8: =SUMIF('QB JOB COST IMPORT'!$I$6:$I$210,A8,'QB JOB COST IMPORT'!$F$6:$F$210) -> 0 | E8: =SUM('DRAW HISTORY'!C8:L8) -> 0 | F8: =IF(H8="Yes",D8-E8,0) -> 0 | G8: =D8-C8 -> 0 | H8: =BUDGET!J8 -> Yes | I8: =IF(D8=0,IF(C8=0,"NO COST / NO BUDGET","NO QB ACTUAL"),"MATCHED") -> NO COST / NO BUDGET | J8: =IF(E8>D8,"PRIOR BILLING EXCEEDS QB ACTUAL",IF(G8>0,"OVER BUDGET","OK")) -> OK
A9: =BUDGET!A9 -> 1070 | B9: =BUDGET!B9 -> Builders Risk Insurance | C9: =BUDGET!H9 -> 0 | D9: =SUMIF('QB JOB COST IMPORT'!$I$6:$I$210,A9,'QB JOB COST IMPORT'!$F$6:$F$210) -> 0 | E9: =SUM('DRAW HISTORY'!C9:L9) -> 0 | F9: =IF(H9="Yes",D9-E9,0) -> 0 | G9: =D9-C9 -> 0 | H9: =BUDGET!J9 -> Yes | I9: =IF(D9=0,IF(C9=0,"NO COST / NO BUDGET","NO QB ACTUAL"),"MATCHED") -> NO COST / NO BUDGET | J9: =IF(E9>D9,"PRIOR BILLING EXCEEDS QB ACTUAL",IF(G9>0,"OVER BUDGET","OK")) -> OK
A10: =BUDGET!A10 -> 1080 | B10: =BUDGET!B10 -> Reinspection Fees | C10: =BUDGET!H10 -> 0 | D10: =SUMIF('QB JOB COST IMPORT'!$I$6:$I$210,A10,'QB JOB COST IMPORT'!$F$6:$F$210) -> 0 | E10: =SUM('DRAW HISTORY'!C10:L10) -> 0 | F10: =IF(H10="Yes",D10-E10,0) -> 0 | G10: =D10-C10 -> 0 | H10: =BUDGET!J10 -> Yes | I10: =IF(D10=0,IF(C10=0,"NO COST / NO BUDGET","NO QB ACTUAL"),"MATCHED") -> NO COST / NO BUDGET | J10: =IF(E10>D10,"PRIOR BILLING EXCEEDS QB ACTUAL",IF(G10>0,"OVER BUDGET","OK")) -> OK
A11: =BUDGET!A11 -> 2010 | B11: =BUDGET!B11 -> Grading - Clear Lot | C11: =BUDGET!H11 -> 0 | D11: =SUMIF('QB JOB COST IMPORT'!$I$6:$I$210,A11,'QB JOB COST IMPORT'!$F$6:$F$210) -> 0 | E11: =SUM('DRAW HISTORY'!C11:L11) -> 0 | F11: =IF(H11="Yes",D11-E11,0) -> 0 | G11: =D11-C11 -> 0 | H11: =BUDGET!J11 -> Yes | I11: =IF(D11=0,IF(C11=0,"NO COST / NO BUDGET","NO QB ACTUAL"),"MATCHED") -> NO COST / NO BUDGET | J11: =IF(E11>D11,"PRIOR BILLING EXCEEDS QB ACTUAL",IF(G11>0,"OVER BUDGET","OK")) -> OK
A12: =BUDGET!A12 -> 2011 | B12: =BUDGET!B12 -> Grading - Haul Debris | C12: =BUDGET!H12 -> 0 | D12: =SUMIF('QB JOB COST IMPORT'!$I$6:$I$210,A12,'QB JOB COST IMPORT'!$F$6:$F$210) -> 0 | E12: =SUM('DRAW HISTORY'!C12:L12) -> 0 | F12: =IF(H12="Yes",D12-E12,0) -> 0 | G12: =D12-C12 -> 0 | H12: =BUDGET!J12 -> Yes | I12: =IF(D12=0,IF(C12=0,"NO COST / NO BUDGET","NO QB ACTUAL"),"MATCHED") -> NO COST / NO BUDGET | J12: =IF(E12>D12,"PRIOR BILLING EXCEEDS QB ACTUAL",IF(G12>0,"OVER BUDGET","OK")) -> OK
A13: =BUDGET!A13 -> 2012 | B13: =BUDGET!B13 -> Grading - Cut Foundation | C13: =BUDGET!H13 -> 0 | D13: =SUMIF('QB JOB COST IMPORT'!$I$6:$I$210,A13,'QB JOB COST IMPORT'!$F$6:$F$210) -> 0 | E13: =SUM('DRAW HISTORY'!C13:L13) -> 0 | F13: =IF(H13="Yes",D13-E13,0) -> 0 | G13: =D13-C13 -> 0 | H13: =BUDGET!J13 -> Yes | I13: =IF(D13=0,IF(C13=0,"NO COST / NO BUDGET","NO QB ACTUAL"),"MATCHED") -> NO COST / NO BUDGET | J13: =IF(E13>D13,"PRIOR BILLING EXCEEDS QB ACTUAL",IF(G13>0,"OVER BUDGET","OK")) -> OK
A14: =BUDGET!A14 -> 2013 | B14: =BUDGET!B14 -> Grading - Backfill Found | C14: =BUDGET!H14 -> 0 | D14: =SUMIF('QB JOB COST IMPORT'!$I$6:$I$210,A14,'QB JOB COST IMPORT'!$F$6:$F$210) -> 0 | E14: =SUM('DRAW HISTORY'!C14:L14) -> 0 | F14: =IF(H14="Yes",D14-E14,0) -> 0 | G14: =D14-C14 -> 0 | H14: =BUDGET!J14 -> Yes | I14: =IF(D14=0,IF(C14=0,"NO COST / NO BUDGET","NO QB ACTUAL"),"MATCHED") -> NO COST / NO BUDGET | J14: =IF(E14>D14,"PRIOR BILLING EXCEEDS QB ACTUAL",IF(G14>0,"OVER BUDGET","OK")) -> OK
A15: =BUDGET!A15 -> 2014 | B15: =BUDGET!B15 -> Grading - Cut Drive | C15: =BUDGET!H15 -> 0 | D15: =SUMIF('QB JOB COST IMPORT'!$I$6:$I$210,A15,'QB JOB COST IMPORT'!$F$6:$F$210) -> 0 | E15: =SUM('DRAW HISTORY'!C15:L15) -> 0 | F15: =IF(H15="Yes",D15-E15,0) -> 0 | G15: =D15-C15 -> 0 | H15: =BUDGET!J15 -> Yes | I15: =IF(D15=0,IF(C15=0,"NO COST / NO BUDGET","NO QB ACTUAL"),"MATCHED") -> NO COST / NO BUDGET | J15: =IF(E15>D15,"PRIOR BILLING EXCEEDS QB ACTUAL",IF(G15>0,"OVER BUDGET","OK")) -> OK
A16: =BUDGET!A16 -> 2015 | B16: =BUDGET!B16 -> Grading - Final | C16: =BUDGET!H16 -> 0 | D16: =SUMIF('QB JOB COST IMPORT'!$I$6:$I$210,A16,'QB JOB COST IMPORT'!$F$6:$F$210) -> 0 | E16: =SUM('DRAW HISTORY'!C16:L16) -> 0 | F16: =IF(H16="Yes",D16-E16,0) -> 0 | G16: =D16-C16 -> 0 | H16: =BUDGET!J16 -> Yes | I16: =IF(D16=0,IF(C16=0,"NO COST / NO BUDGET","NO QB ACTUAL"),"MATCHED") -> NO COST / NO BUDGET | J16: =IF(E16>D16,"PRIOR BILLING EXCEEDS QB ACTUAL",IF(G16>0,"OVER BUDGET","OK")) -> OK
A17: =BUDGET!A17 -> 2016 | B17: =BUDGET!B17 -> Grading - Misc | C17: =BUDGET!H17 -> 0 | D17: =SUMIF('QB JOB COST IMPORT'!$I$6:$I$210,A17,'QB JOB COST IMPORT'!$F$6:$F$210) -> 0 | E17: =SUM('DRAW HISTORY'!C17:L17) -> 0 | F17: =IF(H17="Yes",D17-E17,0) -> 0 | G17: =D17-C17 -> 0 | H17: =BUDGET!J17 -> Yes | I17: =IF(D17=0,IF(C17=0,"NO COST / NO BUDGET","NO QB ACTUAL"),"MATCHED") -> NO COST / NO BUDGET | J17: =IF(E17>D17,"PRIOR BILLING EXCEEDS QB ACTUAL",IF(G17>0,"OVER BUDGET","OK")) -> OK
... A118: =BUDGET!A118 -> 9999 | B118: =BUDGET!B118 -> Transfer WIP to CGS | C118: =BUDGET!H118 -> 0 | D118: =SUMIF('QB JOB COST IMPORT'!$I$6:$I$210,A118,'QB JOB COST IMPORT'!$F$6:$F$210) -> 0 | E118: =SUM('DRAW HISTORY'!C118:L118) -> 0 | F118: =IF(H118="Yes",D118-E118,0) -> 0 | G118: =D118-C118 -> 0 | H118: =BUDGET!J118 -> No | I118: =IF(D118=0,IF(C118=0,"NO COST / NO BUDGET","NO QB ACTUAL"),"MATCHED") -> NO COST / NO BUDGET | J118: =IF(E118>D118,"PRIOR BILLING EXCEEDS QB ACTUAL",IF(G118>0,"OVER BUDGET","OK")) -> OK
A120: BILLABLE TOTALS | C120: =SUMIF(H6:H118,"Yes",C6:C118) -> 0 | D120: =SUMIF(H6:H118,"Yes",D6:D118) -> 0 | E120: =SUMIF(H6:H118,"Yes",E6:E118) -> 0 | F120: =SUMIF(H6:H118,"Yes",F6:F118) -> 0 | G120: =SUMIF(H6:H118,"Yes",G6:G118) -> 0

Sheet DRAW HISTORY
A1: DRAW HISTORY - INVOICED ACTUAL COST BY COST CODE
A3: After sending an invoice, paste VALUES ONLY from COST RECONCILIATION Current Draw Cost into the corresponding draw column below.
A5: Code | B5: Activity | C5: Draw 1 | D5: Draw 2 | E5: Draw 3 | F5: Draw 4 | G5: Draw 5 | H5: Draw 6 | I5: Draw 7 | J5: Draw 8 | K5: Draw 9 | L5: Draw 10
A6: 1010 | B6: Plan / Site Plans | C6: 0 | D6: 0 | E6: 0 | F6: 0 | G6: 0 | H6: 0 | I6: 0 | J6: 0 | K6: 0 | L6: 0
A7: 1011 | B7: Permits/Fees/Water/Sewer | C7: 0 | D7: 0 | E7: 0 | F7: 0 | G7: 0 | H7: 0 | I7: 0 | J7: 0 | K7: 0 | L7: 0
A8: 1020 | B8: Surveys | C8: 0 | D8: 0 | E8: 0 | F8: 0 | G8: 0 | H8: 0 | I8: 0 | J8: 0 | K8: 0 | L8: 0
A9: 1070 | B9: Builders Risk Insurance | C9: 0 | D9: 0 | E9: 0 | F9: 0 | G9: 0 | H9: 0 | I9: 0 | J9: 0 | K9: 0 | L9: 0
A10: 1080 | B10: Reinspection Fees | C10: 0 | D10: 0 | E10: 0 | F10: 0 | G10: 0 | H10: 0 | I10: 0 | J10: 0 | K10: 0 | L10: 0
A11: 2010 | B11: Grading - Clear Lot | C11: 0 | D11: 0 | E11: 0 | F11: 0 | G11: 0 | H11: 0 | I11: 0 | J11: 0 | K11: 0 | L11: 0
A12: 2011 | B12: Grading - Haul Debris | C12: 0 | D12: 0 | E12: 0 | F12: 0 | G12: 0 | H12: 0 | I12: 0 | J12: 0 | K12: 0 | L12: 0
A13: 2012 | B13: Grading - Cut Foundation | C13: 0 | D13: 0 | E13: 0 | F13: 0 | G13: 0 | H13: 0 | I13: 0 | J13: 0 | K13: 0 | L13: 0
A14: 2013 | B14: Grading - Backfill Found | C14: 0 | D14: 0 | E14: 0 | F14: 0 | G14: 0 | H14: 0 | I14: 0 | J14: 0 | K14: 0 | L14: 0
A15: 2014 | B15: Grading - Cut Drive | C15: 0 | D15: 0 | E15: 0 | F15: 0 | G15: 0 | H15: 0 | I15: 0 | J15: 0 | K15: 0 | L15: 0
A16: 2015 | B16: Grading - Final | C16: 0 | D16: 0 | E16: 0 | F16: 0 | G16: 0 | H16: 0 | I16: 0 | J16: 0 | K16: 0 | L16: 0
A17: 2016 | B17: Grading - Misc | C17: 0 | D17: 0 | E17: 0 | F17: 0 | G17: 0 | H17: 0 | I17: 0 | J17: 0 | K17: 0 | L17: 0
... A118: 9999 | B118: Transfer WIP to CGS | C118: 0 | D118: 0 | E118: 0 | F118: 0 | G118: 0 | H118: 0 | I118: 0 | J118: 0 | K118: 0 | L118: 0

Sheet ESTIMATE
A4: ='Project Setup'!B6&" | "&'Project Setup'!B7&" | "&'Project Setup'!B8 -> 7772 Turner Rd. | Woodstock, GA 30188 | (404) 867-7890
A6: ESTIMATE | G6: =IF('Project Setup'!B16="","Estimate #","Estimate # "&'Project Setup'!B16) -> Estimate #
G7: =IF('Project Setup'!B17="","",'Project Setup'!B17)
A8: Estimate for | D8: Payable to
A9: =IF('Project Setup'!B10="","",'Project Setup'!B10) | D9: ='Project Setup'!B5 -> Stone Column Properties, LLC.
A10: =IF('Project Setup'!B11="","",'Project Setup'!B11) | D10: ='Project Setup'!B6&", "&'Project Setup'!B7 -> 7772 Turner Rd., Woodstock, GA 30188
A11: =IF('Project Setup'!B12="","",'Project Setup'!B12) | D11: Project
D12: =IF('Project Setup'!B14="","",'Project Setup'!B14)
A14: ESTIMATED COST CATEGORY | B14: SCOPE / BASIS | H14: ESTIMATED COST
A15: Preconstruction & General | B15: Estimated costs for preconstruction & general based on the current project budget and scope. | H15: =SUMIFS(BUDGET!$H$6:$H$118,BUDGET!$K$6:$K$118,A15,BUDGET!$I$6:$I$118,"Yes") -> 0
A16: Sitework | B16: Estimated costs for sitework based on the current project budget and scope. | H16: =SUMIFS(BUDGET!$H$6:$H$118,BUDGET!$K$6:$K$118,A16,BUDGET!$I$6:$I$118,"Yes") -> 0
A17: Foundation | B17: Estimated costs for foundation based on the current project budget and scope. | H17: =SUMIFS(BUDGET!$H$6:$H$118,BUDGET!$K$6:$K$118,A17,BUDGET!$I$6:$I$118,"Yes") -> 0
A18: Structure, Exterior & MEP | B18: Estimated costs for structure, exterior & mep based on the current project budget and scope. | H18: =SUMIFS(BUDGET!$H$6:$H$118,BUDGET!$K$6:$K$118,A18,BUDGET!$I$6:$I$118,"Yes") -> 0
A19: Interior Finishes | B19: Estimated costs for interior finishes based on the current project budget and scope. | H19: =SUMIFS(BUDGET!$H$6:$H$118,BUDGET!$K$6:$K$118,A19,BUDGET!$I$6:$I$118,"Yes") -> 0
A20: Exterior Improvements & Closeout | B20: Estimated costs for exterior improvements & closeout based on the current project budget and scope. | H20: =SUMIFS(BUDGET!$H$6:$H$118,BUDGET!$K$6:$K$118,A20,BUDGET!$I$6:$I$118,"Yes") -> 0
A21: Other Project Costs | B21: Estimated costs for other project costs based on the current project budget and scope. | H21: =SUMIFS(BUDGET!$H$6:$H$118,BUDGET!$K$6:$K$118,A21,BUDGET!$I$6:$I$118,"Yes") -> 0
A24: ='Project Setup'!B20 -> Cost-plus arrangement. Budget amounts are estimates only. Owner is billed for actual project costs incurred plus the stated project-management fee. | F24: Estimated Hard Costs | H24: =BUDGET!H120 -> 0
F25: ="Management Fee ("&TEXT('Project Setup'!B18,"0%")&")" -> Management Fee (18%) | H25: =BUDGET!H121 -> 0
F27: ESTIMATED PROJECT TOTAL | H27: =BUDGET!H122 -> 0
F29: Estimated Deposit | H29: =H27*'Project Setup'!B19 -> 0
A32: Signature & Date:

Sheet INVOICE
A4: ='Project Setup'!B6&" | "&'Project Setup'!B7&" | "&'Project Setup'!B8 -> 7772 Turner Rd. | Woodstock, GA 30188 | (404) 867-7890
A6: INVOICE | G6: =IF('Project Setup'!B22="","INVOICE","Invoice # "&'Project Setup'!B22&TEXT('Project Setup'!B21,"00")) -> INVOICE
G7: ="Progress Draw "&'Project Setup'!B21 -> Progress Draw 1
A8: Bill to | D8: Payable to | G8: =IF('Project Setup'!B23="","","Invoice date: "&TEXT('Project Setup'!B23,"m/d/yyyy"))
A9: =IF('Project Setup'!B10="","",'Project Setup'!B10) | D9: ='Project Setup'!B5 -> Stone Column Properties, LLC. | G9: =IF('Project Setup'!B24="","","Due: "&TEXT('Project Setup'!B24,"m/d/yyyy"))
A10: =IF('Project Setup'!B11="","",'Project Setup'!B11) | D10: ='Project Setup'!B6&", "&'Project Setup'!B7 -> 7772 Turner Rd., Woodstock, GA 30188
A11: =IF('Project Setup'!B12="","",'Project Setup'!B12) | D11: Project
D12: =IF('Project Setup'!B14="","",'Project Setup'!B14)
A14: ACTUAL COST CATEGORY | B14: CURRENT ACTUAL COST | E14: PRIOR ACTUAL COST | H14: CUMULATIVE ACTUAL
A15: Preconstruction & General | B15: =SUMIFS('COST RECONCILIATION'!$F$6:$F$118,BUDGET!$K$6:$K$118,A15,BUDGET!$J$6:$J$118,"Yes") -> 0 | E15: =SUMIFS('COST RECONCILIATION'!$E$6:$E$118,BUDGET!$K$6:$K$118,A15,BUDGET!$J$6:$J$118,"Yes") -> 0 | H15: =B15+E15 -> 0
A16: Sitework | B16: =SUMIFS('COST RECONCILIATION'!$F$6:$F$118,BUDGET!$K$6:$K$118,A16,BUDGET!$J$6:$J$118,"Yes") -> 0 | E16: =SUMIFS('COST RECONCILIATION'!$E$6:$E$118,BUDGET!$K$6:$K$118,A16,BUDGET!$J$6:$J$118,"Yes") -> 0 | H16: =B16+E16 -> 0
A17: Foundation | B17: =SUMIFS('COST RECONCILIATION'!$F$6:$F$118,BUDGET!$K$6:$K$118,A17,BUDGET!$J$6:$J$118,"Yes") -> 0 | E17: =SUMIFS('COST RECONCILIATION'!$E$6:$E$118,BUDGET!$K$6:$K$118,A17,BUDGET!$J$6:$J$118,"Yes") -> 0 | H17: =B17+E17 -> 0
A18: Structure, Exterior & MEP | B18: =SUMIFS('COST RECONCILIATION'!$F$6:$F$118,BUDGET!$K$6:$K$118,A18,BUDGET!$J$6:$J$118,"Yes") -> 0 | E18: =SUMIFS('COST RECONCILIATION'!$E$6:$E$118,BUDGET!$K$6:$K$118,A18,BUDGET!$J$6:$J$118,"Yes") -> 0 | H18: =B18+E18 -> 0
A19: Interior Finishes | B19: =SUMIFS('COST RECONCILIATION'!$F$6:$F$118,BUDGET!$K$6:$K$118,A19,BUDGET!$J$6:$J$118,"Yes") -> 0 | E19: =SUMIFS('COST RECONCILIATION'!$E$6:$E$118,BUDGET!$K$6:$K$118,A19,BUDGET!$J$6:$J$118,"Yes") -> 0 | H19: =B19+E19 -> 0
A20: Exterior Improvements & Closeout | B20: =SUMIFS('COST RECONCILIATION'!$F$6:$F$118,BUDGET!$K$6:$K$118,A20,BUDGET!$J$6:$J$118,"Yes") -> 0 | E20: =SUMIFS('COST RECONCILIATION'!$E$6:$E$118,BUDGET!$K$6:$K$118,A20,BUDGET!$J$6:$J$118,"Yes") -> 0 | H20: =B20+E20 -> 0
A21: Other Project Costs | B21: =SUMIFS('COST RECONCILIATION'!$F$6:$F$118,BUDGET!$K$6:$K$118,A21,BUDGET!$J$6:$J$118,"Yes") -> 0 | E21: =SUMIFS('COST RECONCILIATION'!$E$6:$E$118,BUDGET!$K$6:$K$118,A21,BUDGET!$J$6:$J$118,"Yes") -> 0 | H21: =B21+E21 -> 0
A24: ="Cost-plus billing based on cumulative QuickBooks actual job costs"&IF('Project Setup'!B23="",""," through "&TEXT('Project Setup'!B23,"m/d/yyyy"))&". Current draw equals cumulative actual cost less actual costs billed on prior draws. Budget figures are estimates only and do not cap actual reimbursable costs."&CHAR(10)&CHAR(10)&"Payment terms: "&'Project Setup'!B26 -> Cost-plus billing based on cumulative QuickBooks actual job costs. Current draw equals cumulative actual cost less actual costs billed on prior draws. Budget figures are estimates only and do not cap actual reimbursable costs. Payment terms: Due upon receipt | E24: New Actual Costs | H24: =SUM(B15:B21) -> 0
E25: ="Management Fee ("&TEXT('Project Setup'!B18,"0%")&")" -> Management Fee (18%) | H25: =H24*'Project Setup'!B18 -> 0
E26: Gross Current Draw | H26: =H24+H25 -> 0
E27: Credit / Deposit Applied | H27: =-'Project Setup'!B25 -> 0
E29: AMOUNT DUE | H29: =H26+H27 -> 0
E31: Previously Billed incl. Fee | H31: =SUM(E15:E21)*(1+'Project Setup'!B18) -> 0
E32: Cumulative Actual incl. Fee | H32: =(SUM(H15:H21))*(1+'Project Setup'!B18) -> 0
A35: See INVOICE DETAIL for the cost-code reconciliation supporting this draw.

Sheet INVOICE DETAIL
A1: INVOICE DETAIL - ACTUAL COST RECONCILIATION
A3: =IF('Project Setup'!B22="","Invoice Detail","Invoice "&'Project Setup'!B22&TEXT('Project Setup'!B21,"00"))&IF('Project Setup'!B14="",""," | "&'Project Setup'!B14)&IF('Project Setup'!B23="",""," | Through "&TEXT('Project Setup'!B23,"m/d/yyyy")) -> Invoice Detail
A5: Code | B5: Cost Category | C5: Estimated Budget | D5: QB Cumulative Actual | E5: Previously Billed | F5: Current Draw Cost | G5: Variance to Budget
A6: ='COST RECONCILIATION'!A6 -> 1010 | B6: ='COST RECONCILIATION'!B6 -> Plan / Site Plans | C6: ='COST RECONCILIATION'!C6 -> 0 | D6: ='COST RECONCILIATION'!D6 -> 0 | E6: ='COST RECONCILIATION'!E6 -> 0 | F6: ='COST RECONCILIATION'!F6 -> 0 | G6: ='COST RECONCILIATION'!G6 -> 0
A7: ='COST RECONCILIATION'!A7 -> 1011 | B7: ='COST RECONCILIATION'!B7 -> Permits/Fees/Water/Sewer | C7: ='COST RECONCILIATION'!C7 -> 0 | D7: ='COST RECONCILIATION'!D7 -> 0 | E7: ='COST RECONCILIATION'!E7 -> 0 | F7: ='COST RECONCILIATION'!F7 -> 0 | G7: ='COST RECONCILIATION'!G7 -> 0
A8: ='COST RECONCILIATION'!A8 -> 1020 | B8: ='COST RECONCILIATION'!B8 -> Surveys | C8: ='COST RECONCILIATION'!C8 -> 0 | D8: ='COST RECONCILIATION'!D8 -> 0 | E8: ='COST RECONCILIATION'!E8 -> 0 | F8: ='COST RECONCILIATION'!F8 -> 0 | G8: ='COST RECONCILIATION'!G8 -> 0
A9: ='COST RECONCILIATION'!A9 -> 1070 | B9: ='COST RECONCILIATION'!B9 -> Builders Risk Insurance | C9: ='COST RECONCILIATION'!C9 -> 0 | D9: ='COST RECONCILIATION'!D9 -> 0 | E9: ='COST RECONCILIATION'!E9 -> 0 | F9: ='COST RECONCILIATION'!F9 -> 0 | G9: ='COST RECONCILIATION'!G9 -> 0
A10: ='COST RECONCILIATION'!A10 -> 1080 | B10: ='COST RECONCILIATION'!B10 -> Reinspection Fees | C10: ='COST RECONCILIATION'!C10 -> 0 | D10: ='COST RECONCILIATION'!D10 -> 0 | E10: ='COST RECONCILIATION'!E10 -> 0 | F10: ='COST RECONCILIATION'!F10 -> 0 | G10: ='COST RECONCILIATION'!G10 -> 0
A11: ='COST RECONCILIATION'!A11 -> 2010 | B11: ='COST RECONCILIATION'!B11 -> Grading - Clear Lot | C11: ='COST RECONCILIATION'!C11 -> 0 | D11: ='COST RECONCILIATION'!D11 -> 0 | E11: ='COST RECONCILIATION'!E11 -> 0 | F11: ='COST RECONCILIATION'!F11 -> 0 | G11: ='COST RECONCILIATION'!G11 -> 0
A12: ='COST RECONCILIATION'!A12 -> 2011 | B12: ='COST RECONCILIATION'!B12 -> Grading - Haul Debris | C12: ='COST RECONCILIATION'!C12 -> 0 | D12: ='COST RECONCILIATION'!D12 -> 0 | E12: ='COST RECONCILIATION'!E12 -> 0 | F12: ='COST RECONCILIATION'!F12 -> 0 | G12: ='COST RECONCILIATION'!G12 -> 0
A13: ='COST RECONCILIATION'!A13 -> 2012 | B13: ='COST RECONCILIATION'!B13 -> Grading - Cut Foundation | C13: ='COST RECONCILIATION'!C13 -> 0 | D13: ='COST RECONCILIATION'!D13 -> 0 | E13: ='COST RECONCILIATION'!E13 -> 0 | F13: ='COST RECONCILIATION'!F13 -> 0 | G13: ='COST RECONCILIATION'!G13 -> 0
A14: ='COST RECONCILIATION'!A14 -> 2013 | B14: ='COST RECONCILIATION'!B14 -> Grading - Backfill Found | C14: ='COST RECONCILIATION'!C14 -> 0 | D14: ='COST RECONCILIATION'!D14 -> 0 | E14: ='COST RECONCILIATION'!E14 -> 0 | F14: ='COST RECONCILIATION'!F14 -> 0 | G14: ='COST RECONCILIATION'!G14 -> 0
A15: ='COST RECONCILIATION'!A15 -> 2014 | B15: ='COST RECONCILIATION'!B15 -> Grading - Cut Drive | C15: ='COST RECONCILIATION'!C15 -> 0 | D15: ='COST RECONCILIATION'!D15 -> 0 | E15: ='COST RECONCILIATION'!E15 -> 0 | F15: ='COST RECONCILIATION'!F15 -> 0 | G15: ='COST RECONCILIATION'!G15 -> 0
A16: ='COST RECONCILIATION'!A16 -> 2015 | B16: ='COST RECONCILIATION'!B16 -> Grading - Final | C16: ='COST RECONCILIATION'!C16 -> 0 | D16: ='COST RECONCILIATION'!D16 -> 0 | E16: ='COST RECONCILIATION'!E16 -> 0 | F16: ='COST RECONCILIATION'!F16 -> 0 | G16: ='COST RECONCILIATION'!G16 -> 0
A17: ='COST RECONCILIATION'!A17 -> 2016 | B17: ='COST RECONCILIATION'!B17 -> Grading - Misc | C17: ='COST RECONCILIATION'!C17 -> 0 | D17: ='COST RECONCILIATION'!D17 -> 0 | E17: ='COST RECONCILIATION'!E17 -> 0 | F17: ='COST RECONCILIATION'!F17 -> 0 | G17: ='COST RECONCILIATION'!G17 -> 0
... A118: ='COST RECONCILIATION'!A118 -> 9999 | B118: ='COST RECONCILIATION'!B118 -> Transfer WIP to CGS | C118: ='COST RECONCILIATION'!C118 -> 0 | D118: ='COST RECONCILIATION'!D118 -> 0 | E118: ='COST RECONCILIATION'!E118 -> 0 | F118: ='COST RECONCILIATION'!F118 -> 0 | G118: ='COST RECONCILIATION'!G118 -> 0
